questfoundry/__init__.py
questfoundry/logging_config.py
questfoundry/logging_extensions.pyi
questfoundry/orchestrator.py
questfoundry/py.typed
questfoundry/version.py
questfoundry/execution/__init__.py
questfoundry/execution/manifest_loader.py
questfoundry/execution/playbook_executor.py
questfoundry/export/__init__.py
questfoundry/export/binder.py
questfoundry/export/git_export.py
questfoundry/export/view.py
questfoundry/lifecycles/__init__.py
questfoundry/lifecycles/base.py
questfoundry/lifecycles/hooks.py
questfoundry/lifecycles/tu.py
questfoundry/loops/__init__.py
questfoundry/loops/base.py
questfoundry/loops/registry.py
questfoundry/models/__init__.py
questfoundry/models/artifact.py
questfoundry/protocol/__init__.py
questfoundry/protocol/client.py
questfoundry/protocol/conformance.py
questfoundry/protocol/envelope.py
questfoundry/protocol/file_transport.py
questfoundry/protocol/transport.py
questfoundry/protocol/types.py
questfoundry/providers/__init__.py
questfoundry/providers/base.py
questfoundry/providers/cache.py
questfoundry/providers/config.py
questfoundry/providers/rate_limiter.py
questfoundry/providers/registry.py
questfoundry/providers/audio/__init__.py
questfoundry/providers/audio/elevenlabs.py
questfoundry/providers/audio/mock.py
questfoundry/providers/image/__init__.py
questfoundry/providers/image/a1111.py
questfoundry/providers/image/dalle.py
questfoundry/providers/image/imagen.py
questfoundry/providers/text/__init__.py
questfoundry/providers/text/bedrock.py
questfoundry/providers/text/gemini.py
questfoundry/providers/text/ollama.py
questfoundry/providers/text/openai.py
questfoundry/resources/__init__.py
questfoundry/resources/manifests/__init__.py
questfoundry/resources/prompts/__init__.py
questfoundry/resources/schemas/__init__.py
questfoundry/resources/schemas/action_items.schema.json
questfoundry/resources/schemas/anchor_map.schema.json
questfoundry/resources/schemas/archive_manifest.schema.json
questfoundry_py-0.7.0.dist-info/METADATA
questfoundry_py-0.7.0.dist-info/WHEEL
questfoundry_py-0.7.0.dist-info/RECORD
