Metadata-Version: 2.4
Name: questfoundry-py
Version: 0.7.0
Summary: Python library for QuestFoundry protocol and artifact management
Project-URL: Homepage, https://github.com/pvliesdonk/questfoundry-py
Project-URL: Documentation, https://github.com/pvliesdonk/questfoundry-spec
Project-URL: Specification, https://github.com/pvliesdonk/questfoundry-spec
Project-URL: Schemas, https://questfoundry.liesdonk.nl/schemas/
Author-email: Peter Liesdonk <peter@liesdonk.nl>
License: MIT
Keywords: artifacts,interactive-fiction,narrative,protocol,questfoundry
Classifier: Development Status :: 3 - Alpha
Classifier: Intended Audience :: Developers
Classifier: License :: OSI Approved :: MIT License
Classifier: Programming Language :: Python :: 3
Classifier: Programming Language :: Python :: 3.11
Classifier: Programming Language :: Python :: 3.12
Classifier: Programming Language :: Python :: 3.13
Classifier: Programming Language :: Python :: 3.14
Classifier: Topic :: Software Development :: Libraries :: Python Modules
Classifier: Typing :: Typed
Requires-Python: >=3.11
Requires-Dist: httpx>=0.25
Requires-Dist: jsonschema>=4.0
Requires-Dist: pydantic>=2.0
Requires-Dist: python-dotenv>=1.0
Requires-Dist: pyyaml>=6.0
Provides-Extra: all-providers
Requires-Dist: google-generativeai>=0.3; extra == 'all-providers'
Requires-Dist: ollama>=0.1; extra == 'all-providers'
Requires-Dist: openai>=1.0; extra == 'all-providers'
Provides-Extra: dev
Requires-Dist: commitizen>=3.12.0; extra == 'dev'
Requires-Dist: mypy>=1.0; extra == 'dev'
Requires-Dist: pre-commit>=3.0; extra == 'dev'
Requires-Dist: pytest-cov>=4.0; extra == 'dev'
Requires-Dist: pytest>=7.0; extra == 'dev'
Requires-Dist: ruff>=0.1.0; extra == 'dev'
Requires-Dist: types-jsonschema>=4.0; extra == 'dev'
Requires-Dist: types-pyyaml>=6.0; extra == 'dev'
Provides-Extra: docs
Requires-Dist: markdown>=3.4; extra == 'docs'
Requires-Dist: mkdocs-material>=9.0.0; extra == 'docs'
Requires-Dist: mkdocs>=1.5.0; extra == 'docs'
Requires-Dist: mkdocstrings[python]>=0.23.0; extra == 'docs'
Requires-Dist: pymdown-extensions>=10.0; extra == 'docs'
Provides-Extra: google
Requires-Dist: google-generativeai>=0.3; extra == 'google'
Provides-Extra: ollama
Requires-Dist: ollama>=0.1; extra == 'ollama'
Provides-Extra: openai
Requires-Dist: openai>=1.0; extra == 'openai'
